sqtIO/__init__.py
sqtIO/sqt_io.py
sqtIO-0.1.1.dist-info/METADATA
sqtIO-0.1.1.dist-info/WHEEL
sqtIO-0.1.1.dist-info/top_level.txt
sqtIO-0.1.1.dist-info/RECORD
