Metadata-Version: 2.1
Name: sqtIO
Version: 0.1.1
Summary: A package for handling SQT format ProLucid search files
Home-page: https://github.com/prashanthciryam/sqtIO
Author: Prashanth Ciryam
Author-email: psciryam@gmail.com
Classifier: Development Status :: 3 - Alpha
Classifier: Intended Audience :: Science/Research
Classifier: License :: OSI Approved :: MIT License
Classifier: Programming Language :: Python :: 3
Classifier: Programming Language :: Python :: 3.6
Classifier: Programming Language :: Python :: 3.7
Classifier: Programming Language :: Python :: 3.8
Classifier: Programming Language :: Python :: 3.9
Classifier: Programming Language :: Python :: 3.10
Classifier: Programming Language :: Python :: 3.11
Requires-Dist: pandas >=1.0.0
